http_tui/__about__.py
http_tui/__main__.py
http_tui/app.css
http_tui-0.0.9.dist-info/METADATA
http_tui-0.0.9.dist-info/WHEEL
http_tui-0.0.9.dist-info/entry_points.txt
http_tui-0.0.9.dist-info/licenses/LICENSE.txt
http_tui-0.0.9.dist-info/RECORD
