Metadata-Version: 2.1
Name: http-tui
Version: 0.0.9
Summary: Perform HTTP requests in a somewhat friendly TUI
Project-URL: Documentation, https://github.com/treyhunner/http-tui#readme
Project-URL: Issues, https://github.com/treyhunner/http-tui/issues
Project-URL: Source, https://github.com/treyhunner/http-tui
Author-email: Trey Hunner <trey@treyhunner.com>
License-Expression: MIT
License-File: LICENSE.txt
Classifier: Development Status :: 4 - Beta
Classifier: Programming Language :: Python
Classifier: Programming Language :: Python :: 3.7
Classifier: Programming Language :: Python :: 3.8
Classifier: Programming Language :: Python :: 3.9
Classifier: Programming Language :: Python :: 3.10
Classifier: Programming Language :: Python :: 3.11
Classifier: Programming Language :: Python :: Implementation :: CPython
Classifier: Programming Language :: Python :: Implementation :: PyPy
Requires-Python: >=3.7
Requires-Dist: requests
Requires-Dist: textual
